bbindex/__init__.py
bbindex/authorize.py
bbindex/base.py
bbindex/dataapi.py
bbindex/vars.py
bbindex-0.1.5.dist-info/DESCRIPTION.rst
bbindex-0.1.5.dist-info/METADATA
bbindex-0.1.5.dist-info/RECORD
bbindex-0.1.5.dist-info/WHEEL
bbindex-0.1.5.dist-info/metadata.json
bbindex-0.1.5.dist-info/top_level.txt
