Metadata-Version: 2.0
Name: bbindex
Version: 0.1.5
Summary: The World's First Well Diversified Crypto Asset Indices
Home-page: http://tushare.org
Author: tushare.org
Author-email: waditu@163.com
License: Apache 2.0
Keywords: Crypto Asset Index
Platform: UNKNOWN
Classifier: Development Status :: 4 - Beta
Classifier: Programming Language :: Python :: 2.6
Classifier: Programming Language :: Python :: 2.7
Classifier: Programming Language :: Python :: 3.2
Classifier: Programming Language :: Python :: 3.3
Classifier: Programming Language :: Python :: 3.4
Classifier: License :: OSI Approved :: BSD License
